zig_codeblocks-0.3.3.dist-info/METADATA
zig_codeblocks-0.3.3.dist-info/WHEEL
zig_codeblocks-0.3.3.dist-info/entry_points.txt
zig_codeblocks-0.3.3.dist-info/licenses/LICENSE
zig_codeblocks.libs/libgcc_s-1e52349c.so.1
zig_codeblocks/__init__.py
zig_codeblocks/__main__.py
zig_codeblocks/_core.cpython-313t-x86_64-linux-musl.so
zig_codeblocks/_core.pyi
zig_codeblocks/py.typed
zig_codeblocks-0.3.3.dist-info/RECORD
