Metadata-Version: 2.4
Name: zig-codeblocks
Version: 0.3.3
Requires-Dist: typer-slim>=0.16.0 ; extra == 'cli'
Provides-Extra: cli
License-File: LICENSE
Summary: Zig ANSI syntax highlighting library
Author-email: trag1c <dev@jakubr.me>
License: MIT
Requires-Python: >=3.9
Project-URL: repository, https://github.com/trag1c/zig-codeblocks
